conda_build_test-0.4.2.dist-info/top_level.txt
conda_build_test-0.4.2.dist-info/RECORD
conda_build_test-0.4.2.dist-info/LICENSE
conda_build_test-0.4.2.dist-info/METADATA
conda_build_test-0.4.2.dist-info/WHEEL
hello/__version__.py
hello/__init__.py
hello/hello.cpython-311-i386-linux-gnu.so
