Metadata-Version: 2.1
Name: conda-build-test
Version: 0.4.2
Summary: Testing packaging and uploading with GitHub actions
Author-email: Christopher Billington <chrisjbillington@gmail.com>
License: Copyright 2024 Chris Billington
Project-URL: Homepage, https://github.com/chrisjbillington/conda-build-test
Project-URL: Documentation, https://github.com/chrisjbillington/conda-build-test
Project-URL: Repository, https://github.com/chrisjbillington/conda-build-test
Project-URL: Downloads, https://github.com/chrisjbillington/conda-build-test/releases
Project-URL: Tracker, https://github.com/chrisjbillington/conda-build-test/issues/
Classifier: Programming Language :: Python :: 3 :: Only
Requires-Python: >=3.8
License-File: LICENSE
Requires-Dist: setuptools_scm
